mdpo/__init__.py
mdpo/cli.py
mdpo/command.py
mdpo/compat.py
mdpo/event.py
mdpo/io.py
mdpo/md.py
mdpo/md4c.py
mdpo/po.py
mdpo/polib.py
mdpo/text.py
mdpo/md2po/__init__.py
mdpo/md2po/__main__.py
mdpo/md2po2md/__init__.py
mdpo/md2po2md/__main__.py
mdpo/mdpo2html/__init__.py
mdpo/mdpo2html/__main__.py
mdpo/po2md/__init__.py
mdpo/po2md/__main__.py
mdpo-2.1.4.dist-info/METADATA
mdpo-2.1.4.dist-info/WHEEL
mdpo-2.1.4.dist-info/entry_points.txt
mdpo-2.1.4.dist-info/licenses/LICENSE
mdpo-2.1.4.dist-info/RECORD
