Metadata-Version: 2.4
Name: mdpo
Version: 2.1.4
Summary: Markdown files translation using PO files.
Project-URL: Source, https://github.com/mondeja/mdpo
Project-URL: Documentation, https://mondeja.github.io/mdpo
Project-URL: Bug tracker, https://github.com/mondeja/mdpo/issues
Project-URL: Changelog, https://github.com/mondeja/mdpo/releases
Author-email: Álvaro Mondéjar Rubio <mondejar1994@gmail.com>
License-Expression: BSD-3-Clause
License-File: LICENSE
Keywords: html,i18n,markdown,po,pofile,translation
Classifier: Development Status :: 5 - Production/Stable
Classifier: Environment :: Console
Classifier: Intended Audience :: Developers
Classifier: License :: OSI Approved :: BSD License
Classifier: Operating System :: OS Independent
Classifier: Programming Language :: Python :: 3.8
Classifier: Programming Language :: Python :: 3.9
Classifier: Programming Language :: Python :: 3.10
Classifier: Programming Language :: Python :: 3.11
Classifier: Programming Language :: Python :: 3.12
Classifier: Programming Language :: Python :: 3.13
Classifier: Topic :: Software Development :: Internationalization
Classifier: Topic :: Text Processing
Classifier: Topic :: Text Processing :: Markup :: Markdown
Requires-Python: <3.14,>=3.8
Requires-Dist: contextlib-chdir<2,>=1
Requires-Dist: importlib-metadata-argparse-version<3,>=2
Requires-Dist: importlib-metadata; python_version < '3.10'
Requires-Dist: md-ulb-pwrap<0.2,>=0.1
Requires-Dist: polib<2,>=1.1
Requires-Dist: pymd4c<2,>=1.3
